[
  {
    "id": "1",
    "title": "Premium Wireless Headphones Promotion",
    "productId": "1",
    "productName": "Wireless Bluetooth Headphones",
    "type": "product",
    "status": "active",
    "budget": 500,
    "spent": 245.5,
    "impressions": 12500,
    "clicks": 340,
    "conversions": 23,
    "ctr": 2.72,
    "cpc": 0.72,
    "startDate": "2024-08-01T00:00:00Z",
    "endDate": "2024-08-31T23:59:59Z",
    "targetCountries": ["USA", "UK", "Germany", "Canada"],
    "targetKeywords": ["wireless headphones", "bluetooth headphones", "premium audio"],
    "createdAt": "2024-08-01T10:00:00Z"
  },
  {
    "id": "2",
    "title": "Smart Watch Summer Sale",
    "productId": "2",
    "productName": "Smart Fitness Watch",
    "type": "product",
    "status": "paused",
    "budget": 300,
    "spent": 180.25,
    "impressions": 8200,
    "clicks": 195,
    "conversions": 12,
    "ctr": 2.38,
    "cpc": 0.92,
    "startDate": "2024-07-15T00:00:00Z",
    "endDate": "2024-08-15T23:59:59Z",
    "targetCountries": ["USA", "Australia", "UK"],
    "targetKeywords": ["smart watch", "fitness tracker", "health monitor"],
    "createdAt": "2024-07-15T09:30:00Z"
  },
  {
    "id": "3",
    "title": "Power Bank Bundle Offer",
    "productId": "3",
    "productName": "Portable Power Bank",
    "type": "product",
    "status": "completed",
    "budget": 200,
    "spent": 200,
    "impressions": 5800,
    "clicks": 145,
    "conversions": 18,
    "ctr": 2.5,
    "cpc": 1.38,
    "startDate": "2024-07-01T00:00:00Z",
    "endDate": "2024-07-31T23:59:59Z",
    "targetCountries": ["USA", "Canada"],
    "targetKeywords": ["power bank", "portable charger", "mobile battery"],
    "createdAt": "2024-07-01T11:15:00Z"
  }
]
